uagents/__init__.py
uagents/agent.py
uagents/asgi.py
uagents/communication.py
uagents/config.py
uagents/context.py
uagents/contrib/__init__.py
uagents/crypto/__init__.py
uagents/dispatch.py
uagents/experimental/__init__.py
uagents/experimental/chat_agent/README.md
uagents/experimental/chat_agent/__init__.py
uagents/experimental/chat_agent/llm.py
uagents/experimental/chat_agent/protocol.py
uagents/experimental/chat_agent/tools.py
uagents/experimental/dialogues/__init__.py
uagents/experimental/mobility/__init__.py
uagents/experimental/mobility/protocols/__init__.py
uagents/experimental/mobility/protocols/base_protocol.py
uagents/experimental/quota/__init__.py
uagents/experimental/search/__init__.py
uagents/mailbox.py
uagents/network.py
uagents/protocol.py
uagents/query.py
uagents/registration.py
uagents/resolver.py
uagents/setup.py
uagents/storage/__init__.py
uagents/types.py
uagents/utils.py
uagents/wallet_messaging.py
uagents-0.23.5.dist-info/METADATA
uagents-0.23.5.dist-info/WHEEL
uagents-0.23.5.dist-info/RECORD
