Metadata-Version: 2.4
Name: uagents
Version: 0.23.5
Summary: Lightweight framework for rapid agent-based development
License: Apache 2.0
Author: Ed FitzGerald
Author-email: edward.fitzgerald@fetch.ai
Requires-Python: >=3.10,<4.0
Classifier: License :: Other/Proprietary License
Classifier: Programming Language :: Python :: 3
Classifier: Programming Language :: Python :: 3.10
Classifier: Programming Language :: Python :: 3.11
Classifier: Programming Language :: Python :: 3.12
Classifier: Programming Language :: Python :: 3.13
Classifier: Programming Language :: Python :: 3.14
Provides-Extra: all
Provides-Extra: llm
Provides-Extra: wallet
Requires-Dist: aiohttp (>=3.8.3,<4.0)
Requires-Dist: cosmpy (>=0.11.0,<0.12.0)
Requires-Dist: fetchai-babble (>=0.4.5) ; extra == "all"
Requires-Dist: fetchai-babble (>=0.4.5) ; extra == "wallet"
Requires-Dist: litellm (>=1.78.6,<2.0) ; extra == "all"
Requires-Dist: litellm (>=1.78.6,<2.0) ; extra == "llm"
Requires-Dist: pydantic (>=2.8,<3.0)
Requires-Dist: uagents-core (>=0.4.0)
Requires-Dist: uvicorn (>=0.30.1,<1.0)
Project-URL: Documentation, https://fetch.ai/docs
Project-URL: Homepage, https://fetch.ai
Project-URL: Repository, https://github.com/fetchai/uAgents
